multiprocessing_tools/__init__.py
multiprocessing_tools/multiprocessing_tools.py
multiprocessing_tools-1.0.4.dist-info/LICENSE
multiprocessing_tools-1.0.4.dist-info/METADATA
multiprocessing_tools-1.0.4.dist-info/WHEEL
multiprocessing_tools-1.0.4.dist-info/top_level.txt
multiprocessing_tools-1.0.4.dist-info/RECORD
